eikeskog_dev/__init__.py
eikeskog_dev/app.py
eikeskog_dev/eikeskog_dev.py
eikeskog_dev-0.0.5.dist-info/METADATA
eikeskog_dev-0.0.5.dist-info/WHEEL
eikeskog_dev-0.0.5.dist-info/top_level.txt
eikeskog_dev-0.0.5.dist-info/RECORD
