Metadata-Version: 2.1
Name: eikeskog-dev
Version: 0.0.5
Summary: Testing purposes
Requires-Dist: requests
